{
  "categorias": [
    {
      "titulo": "Tente Não Rir",
      "link": "https://www.alura.com.br/formacao-front-end",
      "cor": "#6BD1FF",
      "link_extra": {
        "text": "Vídeos do Tente não rir de gatos",
        "url": "/"
      },
      "videos": [
        {
          "titulo": "Procastinando enquanto vê vídeos de gatos na Internet",
          "url": "https://www.youtube.com/watch?v=Ud0bP7EYfoQ"
        },
        {
          "titulo": "TENTE NÃO RIR OS VÍDEOS DE GATOS MAIS ENGRAÇADOS 😽 PARTE 2",
          "url": "https://www.youtube.com/watch?v=zbDQgFtce5M&t=19s"
        },
        {
          "titulo": "TENTE NÃO RIR OS VÍDEOS DE GATOS MAIS ENGRAÇADOS 😽 PARTE 3",
          "url": "https://www.youtube.com/watch?v=eMEZTl-7Vvw&t=5s"
        }
           
      ]
    },
    {
      "titulo": "Coleção Gatos Engraçados",
      "cor": "#00C86F",
      "link_extra": {
        "text": "Coletânea de Vídeos \"Gatos Engraçados\"",
        "url": "https://www.youtube.com/watch?v=VtYrXqQrCt0"
      },
      "videos": [
        {
          "titulo": "Gatos engraçados #7",
          "url": "https://www.youtube.com/watch?v=eE3H_7JwHOs"
        },
        {
          "titulo": "Gatos engraçados #3",
          "url": "https://www.youtube.com/watch?v=F-WOyYAlko4"
        },
        {
          "titulo": "Gatos engraçados #10",
          "url": "https://www.youtube.com/watch?v=9kkIzivnC78"
        },
        {
          "titulo": "Gatos engraçados #4",
          "url": "https://www.youtube.com/watch?v=STnY8Nl9oz0"
        }, 
        {
          "titulo": "Gatos engraçados #11",
          "url": "https://www.youtube.com/watch?v=MD-fIj6pvGc&t=36s"
        }
      ]
    },
    {
      "titulo": "Gatos Assustadaos",
      "cor": "#9cd33b",
      "link_extra": {
        "text": "Vídeos de Gatos Assustados",
        "url": "https://www.youtube.com/watch?v=ugp6PXX0-1M"
      },
      "videos": [
        {
          "titulo": "Gatos assustados 2017 #2",
          "url": "https://www.youtube.com/watch?v=2W878_OHrn0"
        },
        {
          "titulo": "Gatos tomando sustos.",
          "url": "https://www.youtube.com/watch?v=dfsUtqpdL8o"
        },
        {
          "titulo": "Top 10 : Sustos de Gatos",
          "url": "https://www.youtube.com/watch?v=hRHLhde86oc"
        },
        {
          "titulo": "gatos vs sustos",
          "url": "https://www.youtube.com/watch?v=QNboC2dOHRg"
        }
      ]
    },
    {
      "titulo": "Filmes",
      "cor": "orange",
      "videos": [
        {
          "titulo": "Interestellar",
          "url": "https://www.youtube.com/watch?v=frD_IiY_A3E"
        },
        {
          "titulo": "Gattaca",
          "url": "https://www.youtube.com/watch?v=Dl0tYLbrhhs"
        },
        {
          "titulo": "A Chegada",
          "url": "https://www.youtube.com/watch?v=rNciXGzYZms"
        },
        {
          "titulo": "Feitiço do Tempo",
          "url": "https://www.youtube.com/watch?v=zi8d69P9NvI"
        }
      ]
    },
    {
      "titulo": "Games",
      "cor": "red",
      "link_extra": {
        "text": "Formação de Jogos na Alura",
        "url": "https://www.alura.com.br/formacao-jogos-unity"
      },
      "videos": [
        {
          "titulo": "Final Fantasy 7",
          "url": "https://www.youtube.com/watch?v=I_ATSCTnUD8"
        },
        {
          "titulo": "Assassins Creed Valhalla",
          "url": "https://www.youtube.com/watch?v=KDfdjB9uL0U"
        },
        {
          "titulo": "God of War 4",
          "url": "https://www.youtube.com/watch?v=FyIwEFXOcaE"
        },
        {
          "titulo": "Resident Evil 8",
          "url": "https://www.youtube.com/watch?v=JSapXD9vxYA"
        },
        {
          "titulo": "Pokémon Let's Go Pikachu/Eevee",
          "url": "https://www.youtube.com/watch?v=L56q_k2ydrs"
        }
      ]
    },
    {
      "titulo": "Aprendendo a aprender tecnologia",
      "cor": "#6b5be2",
      "link_extra": {
        "text": "Curso sobre aprendizado na Alura",
        "url": "https://alura.com.br/curso-online-aprender-a-aprender-tecnicas-para-seu-autodesenvolvimento"
      },
      "videos": [
        {
          "titulo": "Como estudar melhor?",
          "url": "https://www.youtube.com/watch?v=Is6c9KSGCbk&feature=youtu.be"
        },
        {
          "titulo": "Faculdade",
          "url": "https://www.youtube.com/watch?v=jw06H8esyzQ&feature=youtu.be"
        },
        {
          "titulo": "Frameworks",
          "url": "https://www.youtube.com/watch?v=QzDjdlF1BQI"
        },
        {
          "titulo": "A mágica do Aprendizado",
          "url": "https://www.youtube.com/watch?v=oTEXzpfEpPY"
        },
        {
          "titulo": "Como aprender a programar?",
          "url": "https://www.youtube.com/watch?v=MwCx2qKdbDw&feature=youtu.be"
        }
      ]
    }
  ]
}